{
  "fight_id": "dd229687cb62c871",
  "method": "",
  "round": "",
  "time": "",
  "time_format": "",
  "referee": "",
  "details": [],
  "fighter1": {
    "id": "c9cf753cfdf77fc2",
    "name": "Marcin Tybura",
    "nickname": "Tybur",
    "dob": "09/11/1985",
    "height": 75,
    "weight": 249,
    "reach": 78,
    "stance": "orthodox",
    "stats": {
      "SLpM": 3.57,
      "Str. Acc.:": 49.0,
      "SApM": 3.26,
      "TD. Avg.": 1.42,
      "TD. Acc.": 33.0,
      "TD, Def": 77.0,
      "Sub. Avg.": 0.1,
      "record": {
        "wins": 26,
        "losses": 9,
        "draws": 0
      }
    },
    "timestamp": "2025-02-13 16:42:14",
    "result": "",
    "KD": 0,
    "Sig. str.": {
      "landed": 0,
      "attempted": 0,
      "Head": {
        "landed": 0,
        "attempted": 0
      },
      "Body": {
        "landed": 0,
        "attempted": 0
      },
      "Leg": {
        "landed": 0,
        "attempted": 0
      },
      "Distance": {
        "landed": 0,
        "attempted": 0
      },
      "Clinch": {
        "landed": 0,
        "attempted": 0
      },
      "Ground": {
        "landed": 0,
        "attempted": 0
      }
    },
    "Sig. str. %": 0.0,
    "Total str.": {
      "landed": 0,
      "attempted": 0
    },
    "Td": {
      "landed": 0,
      "attempted": 0
    },
    "Td %": 0.0,
    "Sub. att": 0,
    "Rev.": 0,
    "Ctrl": "",
    "rounds": {},
    "pre_comp": null
  },
  "fighter2": {
    "id": "0d5cc0170c1a7e71",
    "name": "Mick Parkin",
    "nickname": "",
    "dob": "02/10/1995",
    "height": 76,
    "weight": 265,
    "reach": 79,
    "stance": "orthodox",
    "stats": {
      "SLpM": 4.91,
      "Str. Acc.:": 52.0,
      "SApM": 4.15,
      "TD. Avg.": 1.49,
      "TD. Acc.": 41.0,
      "TD, Def": 50.0,
      "Sub. Avg.": 0.3,
      "record": {
        "wins": 10,
        "losses": 0,
        "draws": 0
      }
    },
    "timestamp": "2025-02-13 16:42:15",
    "result": "",
    "KD": 0,
    "Sig. str.": {
      "landed": 0,
      "attempted": 0,
      "Head": {
        "landed": 0,
        "attempted": 0
      },
      "Body": {
        "landed": 0,
        "attempted": 0
      },
      "Leg": {
        "landed": 0,
        "attempted": 0
      },
      "Distance": {
        "landed": 0,
        "attempted": 0
      },
      "Clinch": {
        "landed": 0,
        "attempted": 0
      },
      "Ground": {
        "landed": 0,
        "attempted": 0
      }
    },
    "Sig. str. %": 0.0,
    "Total str.": {
      "landed": 0,
      "attempted": 0
    },
    "Td": {
      "landed": 0,
      "attempted": 0
    },
    "Td %": 0.0,
    "Sub. att": 0,
    "Rev.": 0,
    "Ctrl": "",
    "rounds": {},
    "pre_comp": null
  }
}