{
  "event_id": "be5aab761c40ef35",
  "date": "2022-10-29",
  "location": {
    "name": "Las Vegas, Nevada, USA",
    "coordinates": {
      "lat": 36.171563,
      "lng": -115.1391009
    },
    "elevation": 611.1660766601562
  },
  "fights": [
    {
      "fight_id": "a554a72bb0377213",
      "method": "KO/TKO",
      "round": "2",
      "time": "0:08",
      "time_format": "5 Rnd (5-5-5-5-5)",
      "referee": "Herb Dean",
      "details": [],
      "fighter1": {
        "id": "751de04455cfaac0",
        "name": "Calvin Kattar",
        "nickname": "",
        "dob": "26/03/1988",
        "height": 71,
        "weight": 145,
        "reach": 72,
        "stance": "orthodox",
        "stats": {
          "SLpM": 4.76,
          "Str. Acc.:": 39.0,
          "SApM": 6.75,
          "TD. Avg.": 0.39,
          "TD. Acc.": 29.0,
          "TD, Def": 72.0,
          "Sub. Avg.": 0.1,
          "record": {
            "wins": 23,
            "losses": 8,
            "draws": 0
          }
        },
        "timestamp": "2025-02-10 14:30:33",
        "result": "L",
        "KD": 0,
        "Sig. str.": {
          "landed": 14,
          "attempted": 58,
          "Head": {
            "landed": 5,
            "attempted": 47
          },
          "Body": {
            "landed": 6,
            "attempted": 8
          },
          "Leg": {
            "landed": 3,
            "attempted": 3
          },
          "Distance": {
            "landed": 14,
            "attempted": 58
          },
          "Clinch": {
            "landed": 0,
            "attempted": 0
          },
          "Ground": {
            "landed": 0,
            "attempted": 0
          }
        },
        "Sig. str. %": 24.0,
        "Total str.": {
          "landed": 14,
          "attempted": 58
        },
        "Td": {
          "landed": 0,
          "attempted": 0
        },
        "Td %": "---",
        "Sub. att": "0",
        "Rev.": "0",
        "Ctrl": "0:00",
        "rounds": {
          "round1": {
            "KD": 0,
            "Sig. str.": {
              "landed": 14,
              "attempted": 57,
              "Head": {
                "landed": 5,
                "attempted": 46
              },
              "Body": {
                "landed": 6,
                "attempted": 8
              },
              "Leg": {
                "landed": 3,
                "attempted": 3
              },
              "Distance": {
                "landed": 14,
                "attempted": 57
              },
              "Clinch": {
                "landed": 0,
                "attempted": 0
              },
              "Ground": {
                "landed": 0,
                "attempted": 0
              }
            },
            "Sig. str. %": 24.0,
            "Total str.": {
              "landed": 14,
              "attempted": 57
            },
            "Td": {
              "landed": 0,
              "attempted": 0
            },
            "Td %": 0,
            "Sub. att": 0,
            "Rev.": 0,
            "Ctrl": 0
          },
          "round2": {
            "KD": 0,
            "Sig. str.": {
              "landed": 0,
              "attempted": 1,
              "Head": {
                "landed": 0,
                "attempted": 1
              },
              "Body": {
                "landed": 0,
                "attempted": 0
              },
              "Leg": {
                "landed": 0,
                "attempted": 0
              },
              "Distance": {
                "landed": 0,
                "attempted": 1
              },
              "Clinch": {
                "landed": 0,
                "attempted": 0
              },
              "Ground": {
                "landed": 0,
                "attempted": 0
              }
            },
            "Sig. str. %": 0.0,
            "Total str.": {
              "landed": 0,
              "attempted": 1
            },
            "Td": {
              "landed": 0,
              "attempted": 0
            },
            "Td %": 0,
            "Sub. att": 0,
            "Rev.": 0,
            "Ctrl": 0
          }
        },
        "pre_comp": null
      },
      "fighter2": {
        "id": "040a74bb0a465c54",
        "name": "Arnold Allen",
        "nickname": "Almighty",
        "dob": "22/01/1994",
        "height": 68,
        "weight": 145,
        "reach": 70,
        "stance": "southpaw",
        "stats": {
          "SLpM": 3.45,
          "Str. Acc.:": 41.0,
          "SApM": 2.88,
          "TD. Avg.": 0.93,
          "TD. Acc.": 47.0,
          "TD, Def": 75.0,
          "Sub. Avg.": 0.3,
          "record": {
            "wins": 20,
            "losses": 3,
            "draws": 0
          }
        },
        "timestamp": "2025-02-10 14:30:34",
        "result": "W",
        "KD": 0,
        "Sig. str.": {
          "landed": 28,
          "attempted": 67,
          "Head": {
            "landed": 21,
            "attempted": 55
          },
          "Body": {
            "landed": 2,
            "attempted": 5
          },
          "Leg": {
            "landed": 5,
            "attempted": 7
          },
          "Distance": {
            "landed": 27,
            "attempted": 62
          },
          "Clinch": {
            "landed": 0,
            "attempted": 0
          },
          "Ground": {
            "landed": 1,
            "attempted": 5
          }
        },
        "Sig. str. %": 41.0,
        "Total str.": {
          "landed": 28,
          "attempted": 67
        },
        "Td": {
          "landed": 0,
          "attempted": 0
        },
        "Td %": "---",
        "Sub. att": "0",
        "Rev.": "0",
        "Ctrl": "0:23",
        "rounds": {
          "round1": {
            "KD": 0,
            "Sig. str.": {
              "landed": 27,
              "attempted": 65,
              "Head": {
                "landed": 21,
                "attempted": 54
              },
              "Body": {
                "landed": 2,
                "attempted": 5
              },
              "Leg": {
                "landed": 4,
                "attempted": 6
              },
              "Distance": {
                "landed": 26,
                "attempted": 60
              },
              "Clinch": {
                "landed": 0,
                "attempted": 0
              },
              "Ground": {
                "landed": 1,
                "attempted": 5
              }
            },
            "Sig. str. %": 41.0,
            "Total str.": {
              "landed": 27,
              "attempted": 65
            },
            "Td": {
              "landed": 0,
              "attempted": 0
            },
            "Td %": 0,
            "Sub. att": 0,
            "Rev.": 0,
            "Ctrl": 23
          },
          "round2": {
            "KD": 0,
            "Sig. str.": {
              "landed": 1,
              "attempted": 2,
              "Head": {
                "landed": 0,
                "attempted": 1
              },
              "Body": {
                "landed": 0,
                "attempted": 0
              },
              "Leg": {
                "landed": 1,
                "attempted": 1
              },
              "Distance": {
                "landed": 1,
                "attempted": 2
              },
              "Clinch": {
                "landed": 0,
                "attempted": 0
              },
              "Ground": {
                "landed": 0,
                "attempted": 0
              }
            },
            "Sig. str. %": 50.0,
            "Total str.": {
              "landed": 1,
              "attempted": 2
            },
            "Td": {
              "landed": 0,
              "attempted": 0
            },
            "Td %": 0,
            "Sub. att": 0,
            "Rev.": 0,
            "Ctrl": 0
          }
        },
        "pre_comp": null
      }
    },
    {
      "fight_id": "bf59d9f8bd9536f3",
      "method": "Decision - Split",
      "round": "3",
      "time": "5:00",
      "time_format": "3 Rnd (5-5-5)",
      "referee": "Dan Miragliotta",
      "details": [
        {
          "judge": "Ben Cartlidge",
          "score": "28 - 29."
        },
        {
          "judge": "Eric Colon",
          "score": "29 - 28."
        },
        {
          "judge": "Derek Cleary",
          "score": "27 - 30."
        }
      ],
      "fighter1": {
        "id": "4b47e71384a9522f",
        "name": "Tim Means",
        "nickname": "The Dirty Bird",
        "dob": "20/02/1984",
        "height": 74,
        "weight": 170,
        "reach": 75,
        "stance": "orthodox",
        "stats": {
          "SLpM": 5.04,
          "Str. Acc.:": 49.0,
          "SApM": 3.65,
          "TD. Avg.": 1.14,
          "TD. Acc.": 40.0,
          "TD, Def": 64.0,
          "Sub. Avg.": 0.2,
          "record": {
            "wins": 33,
            "losses": 17,
            "draws": 1
          }
        },
        "timestamp": "2025-02-10 14:30:36",
        "result": "L",
        "KD": 0,
        "Sig. str.": {
          "landed": 47,
          "attempted": 115,
          "Head": {
            "landed": 18,
            "attempted": 64
          },
          "Body": {
            "landed": 18,
            "attempted": 36
          },
          "Leg": {
            "landed": 11,
            "attempted": 15
          },
          "Distance": {
            "landed": 37,
            "attempted": 103
          },
          "Clinch": {
            "landed": 7,
            "attempted": 9
          },
          "Ground": {
            "landed": 3,
            "attempted": 3
          }
        },
        "Sig. str. %": 40.0,
        "Total str.": {
          "landed": 143,
          "attempted": 215
        },
        "Td": {
          "landed": 3,
          "attempted": 5
        },
        "Td %": 60.0,
        "Sub. att": "0",
        "Rev.": "0",
        "Ctrl": "1:27",
        "rounds": {
          "round1": {
            "KD": 0,
            "Sig. str.": {
              "landed": 17,
              "attempted": 49,
              "Head": {
                "landed": 8,
                "attempted": 27
              },
              "Body": {
                "landed": 3,
                "attempted": 14
              },
              "Leg": {
                "landed": 6,
                "attempted": 8
              },
              "Distance": {
                "landed": 13,
                "attempted": 43
              },
              "Clinch": {
                "landed": 4,
                "attempted": 6
              },
              "Ground": {
                "landed": 0,
                "attempted": 0
              }
            },
            "Sig. str. %": 34.0,
            "Total str.": {
              "landed": 21,
              "attempted": 53
            },
            "Td": {
              "landed": 0,
              "attempted": 0
            },
            "Td %": 0,
            "Sub. att": 0,
            "Rev.": 0,
            "Ctrl": 26
          },
          "round2": {
            "KD": 0,
            "Sig. str.": {
              "landed": 20,
              "attempted": 53,
              "Head": {
                "landed": 7,
                "attempted": 32
              },
              "Body": {
                "landed": 8,
                "attempted": 15
              },
              "Leg": {
                "landed": 5,
                "attempted": 6
              },
              "Distance": {
                "landed": 20,
                "attempted": 53
              },
              "Clinch": {
                "landed": 0,
                "attempted": 0
              },
              "Ground": {
                "landed": 0,
                "attempted": 0
              }
            },
            "Sig. str. %": 37.0,
            "Total str.": {
              "landed": 48,
              "attempted": 83
            },
            "Td": {
              "landed": 0,
              "attempted": 0
            },
            "Td %": 0,
            "Sub. att": 0,
            "Rev.": 0,
            "Ctrl": 0
          },
          "round3": {
            "KD": 0,
            "Sig. str.": {
              "landed": 10,
              "attempted": 13,
              "Head": {
                "landed": 3,
                "attempted": 5
              },
              "Body": {
                "landed": 7,
                "attempted": 7
              },
              "Leg": {
                "landed": 0,
                "attempted": 1
              },
              "Distance": {
                "landed": 4,
                "attempted": 7
              },
              "Clinch": {
                "landed": 3,
                "attempted": 3
              },
              "Ground": {
                "landed": 3,
                "attempted": 3
              }
            },
            "Sig. str. %": 76.0,
            "Total str.": {
              "landed": 74,
              "attempted": 79
            },
            "Td": {
              "landed": 3,
              "attempted": 5
            },
            "Td %": 60.0,
            "Sub. att": 0,
            "Rev.": 0,
            "Ctrl": 61
          }
        },
        "pre_comp": null
      },
      "fighter2": {
        "id": "b0d6a1d8ac3d563d",
        "name": "Max Griffin",
        "nickname": "Pain",
        "dob": "29/11/1985",
        "height": 71,
        "weight": 170,
        "reach": 76,
        "stance": "orthodox",
        "stats": {
          "SLpM": 3.75,
          "Str. Acc.:": 48.0,
          "SApM": 3.66,
          "TD. Avg.": 1.37,
          "TD. Acc.": 40.0,
          "TD, Def": 69.0,
          "Sub. Avg.": 0.3,
          "record": {
            "wins": 20,
            "losses": 11,
            "draws": 0
          }
        },
        "timestamp": "2025-02-10 14:30:37",
        "result": "W",
        "KD": 1,
        "Sig. str.": {
          "landed": 42,
          "attempted": 78,
          "Head": {
            "landed": 25,
            "attempted": 52
          },
          "Body": {
            "landed": 9,
            "attempted": 15
          },
          "Leg": {
            "landed": 8,
            "attempted": 11
          },
          "Distance": {
            "landed": 35,
            "attempted": 66
          },
          "Clinch": {
            "landed": 1,
            "attempted": 1
          },
          "Ground": {
            "landed": 6,
            "attempted": 11
          }
        },
        "Sig. str. %": 53.0,
        "Total str.": {
          "landed": 56,
          "attempted": 96
        },
        "Td": {
          "landed": 3,
          "attempted": 6
        },
        "Td %": 50.0,
        "Sub. att": "0",
        "Rev.": "0",
        "Ctrl": "5:13",
        "rounds": {
          "round1": {
            "KD": 1,
            "Sig. str.": {
              "landed": 25,
              "attempted": 42,
              "Head": {
                "landed": 16,
                "attempted": 29
              },
              "Body": {
                "landed": 7,
                "attempted": 9
              },
              "Leg": {
                "landed": 2,
                "attempted": 4
              },
              "Distance": {
                "landed": 20,
                "attempted": 34
              },
              "Clinch": {
                "landed": 1,
                "attempted": 1
              },
              "Ground": {
                "landed": 4,
                "attempted": 7
              }
            },
            "Sig. str. %": 59.0,
            "Total str.": {
              "landed": 26,
              "attempted": 43
            },
            "Td": {
              "landed": 0,
              "attempted": 2
            },
            "Td %": 0.0,
            "Sub. att": 0,
            "Rev.": 0,
            "Ctrl": 54
          },
          "round2": {
            "KD": 0,
            "Sig. str.": {
              "landed": 13,
              "attempted": 29,
              "Head": {
                "landed": 5,
                "attempted": 16
              },
              "Body": {
                "landed": 2,
                "attempted": 6
              },
              "Leg": {
                "landed": 6,
                "attempted": 7
              },
              "Distance": {
                "landed": 13,
                "attempted": 29
              },
              "Clinch": {
                "landed": 0,
                "attempted": 0
              },
              "Ground": {
                "landed": 0,
                "attempted": 0
              }
            },
            "Sig. str. %": 44.0,
            "Total str.": {
              "landed": 14,
              "attempted": 31
            },
            "Td": {
              "landed": 1,
              "attempted": 2
            },
            "Td %": 50.0,
            "Sub. att": 0,
            "Rev.": 0,
            "Ctrl": 35
          },
          "round3": {
            "KD": 0,
            "Sig. str.": {
              "landed": 4,
              "attempted": 7,
              "Head": {
                "landed": 4,
                "attempted": 7
              },
              "Body": {
                "landed": 0,
                "attempted": 0
              },
              "Leg": {
                "landed": 0,
                "attempted": 0
              },
              "Distance": {
                "landed": 2,
                "attempted": 3
              },
              "Clinch": {
                "landed": 0,
                "attempted": 0
              },
              "Ground": {
                "landed": 2,
                "attempted": 4
              }
            },
            "Sig. str. %": 57.0,
            "Total str.": {
              "landed": 16,
              "attempted": 22
            },
            "Td": {
              "landed": 2,
              "attempted": 2
            },
            "Td %": 100.0,
            "Sub. att": 0,
            "Rev.": 0,
            "Ctrl": 224
          }
        },
        "pre_comp": null
      }
    },
    {
      "fight_id": "5b6bdaf89e493674",
      "method": "Decision - Unanimous",
      "round": "3",
      "time": "5:00",
      "time_format": "3 Rnd (5-5-5)",
      "referee": "Mark Smith",
      "details": [
        {
          "judge": "Ron McCarthy",
          "score": "27 - 30."
        },
        {
          "judge": "Junichiro Kamijo",
          "score": "28 - 29."
        },
        {
          "judge": "Tony Weeks",
          "score": "28 - 29."
        }
      ],
      "fighter1": {
        "id": "fc08099550072fe4",
        "name": "Waldo Cortes-Acosta",
        "nickname": "Salsa Boy",
        "dob": "03/10/1991",
        "height": 76,
        "weight": 260,
        "reach": 78,
        "stance": "orthodox",
        "stats": {
          "SLpM": 5.64,
          "Str. Acc.:": 48.0,
          "SApM": 3.6,
          "TD. Avg.": 0.55,
          "TD. Acc.": 60.0,
          "TD, Def": 60.0,
          "Sub. Avg.": 0.2,
          "record": {
            "wins": 12,
            "losses": 1,
            "draws": 0
          }
        },
        "timestamp": "2025-02-10 14:30:39",
        "result": "W",
        "KD": 0,
        "Sig. str.": {
          "landed": 73,
          "attempted": 158,
          "Head": {
            "landed": 41,
            "attempted": 117
          },
          "Body": {
            "landed": 26,
            "attempted": 32
          },
          "Leg": {
            "landed": 6,
            "attempted": 9
          },
          "Distance": {
            "landed": 73,
            "attempted": 157
          },
          "Clinch": {
            "landed": 0,
            "attempted": 1
          },
          "Ground": {
            "landed": 0,
            "attempted": 0
          }
        },
        "Sig. str. %": 46.0,
        "Total str.": {
          "landed": 73,
          "attempted": 158
        },
        "Td": {
          "landed": 0,
          "attempted": 0
        },
        "Td %": "---",
        "Sub. att": "0",
        "Rev.": "0",
        "Ctrl": "0:03",
        "rounds": {
          "round1": {
            "KD": 0,
            "Sig. str.": {
              "landed": 22,
              "attempted": 39,
              "Head": {
                "landed": 12,
                "attempted": 26
              },
              "Body": {
                "landed": 9,
                "attempted": 12
              },
              "Leg": {
                "landed": 1,
                "attempted": 1
              },
              "Distance": {
                "landed": 22,
                "attempted": 39
              },
              "Clinch": {
                "landed": 0,
                "attempted": 0
              },
              "Ground": {
                "landed": 0,
                "attempted": 0
              }
            },
            "Sig. str. %": 56.0,
            "Total str.": {
              "landed": 22,
              "attempted": 39
            },
            "Td": {
              "landed": 0,
              "attempted": 0
            },
            "Td %": 0,
            "Sub. att": 0,
            "Rev.": 0,
            "Ctrl": 0
          },
          "round2": {
            "KD": 0,
            "Sig. str.": {
              "landed": 25,
              "attempted": 53,
              "Head": {
                "landed": 9,
                "attempted": 33
              },
              "Body": {
                "landed": 12,
                "attempted": 15
              },
              "Leg": {
                "landed": 4,
                "attempted": 5
              },
              "Distance": {
                "landed": 25,
                "attempted": 52
              },
              "Clinch": {
                "landed": 0,
                "attempted": 1
              },
              "Ground": {
                "landed": 0,
                "attempted": 0
              }
            },
            "Sig. str. %": 47.0,
            "Total str.": {
              "landed": 25,
              "attempted": 53
            },
            "Td": {
              "landed": 0,
              "attempted": 0
            },
            "Td %": 0,
            "Sub. att": 0,
            "Rev.": 0,
            "Ctrl": 3
          },
          "round3": {
            "KD": 0,
            "Sig. str.": {
              "landed": 26,
              "attempted": 66,
              "Head": {
                "landed": 20,
                "attempted": 58
              },
              "Body": {
                "landed": 5,
                "attempted": 5
              },
              "Leg": {
                "landed": 1,
                "attempted": 3
              },
              "Distance": {
                "landed": 26,
                "attempted": 66
              },
              "Clinch": {
                "landed": 0,
                "attempted": 0
              },
              "Ground": {
                "landed": 0,
                "attempted": 0
              }
            },
            "Sig. str. %": 39.0,
            "Total str.": {
              "landed": 26,
              "attempted": 66
            },
            "Td": {
              "landed": 0,
              "attempted": 0
            },
            "Td %": 0,
            "Sub. att": 0,
            "Rev.": 0,
            "Ctrl": 0
          }
        },
        "pre_comp": null
      },
      "fighter2": {
        "id": "2b68d9f125d07b42",
        "name": "Jared Vanderaa",
        "nickname": "",
        "dob": "12/05/1992",
        "height": 76,
        "weight": 265,
        "reach": 80,
        "stance": "orthodox",
        "stats": {
          "SLpM": 4.96,
          "Str. Acc.:": 44.0,
          "SApM": 5.67,
          "TD. Avg.": 0.18,
          "TD. Acc.": 50.0,
          "TD, Def": 20.0,
          "Sub. Avg.": 0.0,
          "record": {
            "wins": 12,
            "losses": 10,
            "draws": 0
          }
        },
        "timestamp": "2025-02-10 14:30:40",
        "result": "L",
        "KD": 0,
        "Sig. str.": {
          "landed": 56,
          "attempted": 138,
          "Head": {
            "landed": 12,
            "attempted": 92
          },
          "Body": {
            "landed": 5,
            "attempted": 5
          },
          "Leg": {
            "landed": 39,
            "attempted": 41
          },
          "Distance": {
            "landed": 52,
            "attempted": 128
          },
          "Clinch": {
            "landed": 4,
            "attempted": 10
          },
          "Ground": {
            "landed": 0,
            "attempted": 0
          }
        },
        "Sig. str. %": 40.0,
        "Total str.": {
          "landed": 59,
          "attempted": 143
        },
        "Td": {
          "landed": 0,
          "attempted": 1
        },
        "Td %": 0.0,
        "Sub. att": "0",
        "Rev.": "0",
        "Ctrl": "0:13",
        "rounds": {
          "round1": {
            "KD": 0,
            "Sig. str.": {
              "landed": 13,
              "attempted": 36,
              "Head": {
                "landed": 1,
                "attempted": 24
              },
              "Body": {
                "landed": 0,
                "attempted": 0
              },
              "Leg": {
                "landed": 12,
                "attempted": 12
              },
              "Distance": {
                "landed": 13,
                "attempted": 36
              },
              "Clinch": {
                "landed": 0,
                "attempted": 0
              },
              "Ground": {
                "landed": 0,
                "attempted": 0
              }
            },
            "Sig. str. %": 36.0,
            "Total str.": {
              "landed": 13,
              "attempted": 36
            },
            "Td": {
              "landed": 0,
              "attempted": 0
            },
            "Td %": 0,
            "Sub. att": 0,
            "Rev.": 0,
            "Ctrl": 0
          },
          "round2": {
            "KD": 0,
            "Sig. str.": {
              "landed": 21,
              "attempted": 51,
              "Head": {
                "landed": 4,
                "attempted": 33
              },
              "Body": {
                "landed": 4,
                "attempted": 4
              },
              "Leg": {
                "landed": 13,
                "attempted": 14
              },
              "Distance": {
                "landed": 17,
                "attempted": 41
              },
              "Clinch": {
                "landed": 4,
                "attempted": 10
              },
              "Ground": {
                "landed": 0,
                "attempted": 0
              }
            },
            "Sig. str. %": 41.0,
            "Total str.": {
              "landed": 24,
              "attempted": 56
            },
            "Td": {
              "landed": 0,
              "attempted": 1
            },
            "Td %": 0.0,
            "Sub. att": 0,
            "Rev.": 0,
            "Ctrl": 13
          },
          "round3": {
            "KD": 0,
            "Sig. str.": {
              "landed": 22,
              "attempted": 51,
              "Head": {
                "landed": 7,
                "attempted": 35
              },
              "Body": {
                "landed": 1,
                "attempted": 1
              },
              "Leg": {
                "landed": 14,
                "attempted": 15
              },
              "Distance": {
                "landed": 22,
                "attempted": 51
              },
              "Clinch": {
                "landed": 0,
                "attempted": 0
              },
              "Ground": {
                "landed": 0,
                "attempted": 0
              }
            },
            "Sig. str. %": 43.0,
            "Total str.": {
              "landed": 22,
              "attempted": 51
            },
            "Td": {
              "landed": 0,
              "attempted": 0
            },
            "Td %": 0,
            "Sub. att": 0,
            "Rev.": 0,
            "Ctrl": 0
          }
        },
        "pre_comp": null
      }
    },
    {
      "fight_id": "6a7db3750822d7be",
      "method": "Submission",
      "round": "2",
      "time": "0:49",
      "time_format": "3 Rnd (5-5-5)",
      "referee": "Chris Tognoni",
      "details": [],
      "fighter1": {
        "id": "ca43de99b07b6b40",
        "name": "Josh Fremd",
        "nickname": "",
        "dob": "15/01/1994",
        "height": 76,
        "weight": 185,
        "reach": 76,
        "stance": "orthodox",
        "stats": {
          "SLpM": 2.52,
          "Str. Acc.:": 44.0,
          "SApM": 2.23,
          "TD. Avg.": 0.66,
          "TD. Acc.": 25.0,
          "TD, Def": 30.0,
          "Sub. Avg.": 1.1,
          "record": {
            "wins": 11,
            "losses": 6,
            "draws": 0
          }
        },
        "timestamp": "2025-02-10 14:30:42",
        "result": "L",
        "KD": 0,
        "Sig. str.": {
          "landed": 24,
          "attempted": 54,
          "Head": {
            "landed": 8,
            "attempted": 35
          },
          "Body": {
            "landed": 11,
            "attempted": 14
          },
          "Leg": {
            "landed": 5,
            "attempted": 5
          },
          "Distance": {
            "landed": 20,
            "attempted": 47
          },
          "Clinch": {
            "landed": 4,
            "attempted": 7
          },
          "Ground": {
            "landed": 0,
            "attempted": 0
          }
        },
        "Sig. str. %": 44.0,
        "Total str.": {
          "landed": 27,
          "attempted": 57
        },
        "Td": {
          "landed": 0,
          "attempted": 1
        },
        "Td %": 0.0,
        "Sub. att": "0",
        "Rev.": "0",
        "Ctrl": "0:39",
        "rounds": {
          "round1": {
            "KD": 0,
            "Sig. str.": {
              "landed": 18,
              "attempted": 40,
              "Head": {
                "landed": 4,
                "attempted": 24
              },
              "Body": {
                "landed": 10,
                "attempted": 12
              },
              "Leg": {
                "landed": 4,
                "attempted": 4
              },
              "Distance": {
                "landed": 14,
                "attempted": 33
              },
              "Clinch": {
                "landed": 4,
                "attempted": 7
              },
              "Ground": {
                "landed": 0,
                "attempted": 0
              }
            },
            "Sig. str. %": 45.0,
            "Total str.": {
              "landed": 21,
              "attempted": 43
            },
            "Td": {
              "landed": 0,
              "attempted": 0
            },
            "Td %": 0,
            "Sub. att": 0,
            "Rev.": 0,
            "Ctrl": 30
          },
          "round2": {
            "KD": 0,
            "Sig. str.": {
              "landed": 6,
              "attempted": 14,
              "Head": {
                "landed": 4,
                "attempted": 11
              },
              "Body": {
                "landed": 1,
                "attempted": 2
              },
              "Leg": {
                "landed": 1,
                "attempted": 1
              },
              "Distance": {
                "landed": 6,
                "attempted": 14
              },
              "Clinch": {
                "landed": 0,
                "attempted": 0
              },
              "Ground": {
                "landed": 0,
                "attempted": 0
              }
            },
            "Sig. str. %": 42.0,
            "Total str.": {
              "landed": 6,
              "attempted": 14
            },
            "Td": {
              "landed": 0,
              "attempted": 1
            },
            "Td %": 0.0,
            "Sub. att": 0,
            "Rev.": 0,
            "Ctrl": 9
          }
        },
        "pre_comp": null
      },
      "fighter2": {
        "id": "147e70aa6cc48cfc",
        "name": "Tresean Gore",
        "nickname": "Mr. Vicious",
        "dob": "21/06/1994",
        "height": 72,
        "weight": 185,
        "reach": 75,
        "stance": "switch",
        "stats": {
          "SLpM": 3.0,
          "Str. Acc.:": 54.0,
          "SApM": 5.88,
          "TD. Avg.": 3.46,
          "TD. Acc.": 75.0,
          "TD, Def": 83.0,
          "Sub. Avg.": 1.7,
          "record": {
            "wins": 6,
            "losses": 2,
            "draws": 0
          }
        },
        "timestamp": "2025-02-10 14:30:43",
        "result": "W",
        "KD": 0,
        "Sig. str.": {
          "landed": 10,
          "attempted": 20,
          "Head": {
            "landed": 7,
            "attempted": 14
          },
          "Body": {
            "landed": 1,
            "attempted": 2
          },
          "Leg": {
            "landed": 2,
            "attempted": 4
          },
          "Distance": {
            "landed": 9,
            "attempted": 15
          },
          "Clinch": {
            "landed": 1,
            "attempted": 5
          },
          "Ground": {
            "landed": 0,
            "attempted": 0
          }
        },
        "Sig. str. %": 50.0,
        "Total str.": {
          "landed": 14,
          "attempted": 25
        },
        "Td": {
          "landed": 3,
          "attempted": 4
        },
        "Td %": 75.0,
        "Sub. att": "1",
        "Rev.": "0",
        "Ctrl": "2:46",
        "rounds": {
          "round1": {
            "KD": 0,
            "Sig. str.": {
              "landed": 8,
              "attempted": 14,
              "Head": {
                "landed": 6,
                "attempted": 9
              },
              "Body": {
                "landed": 1,
                "attempted": 2
              },
              "Leg": {
                "landed": 1,
                "attempted": 3
              },
              "Distance": {
                "landed": 7,
                "attempted": 9
              },
              "Clinch": {
                "landed": 1,
                "attempted": 5
              },
              "Ground": {
                "landed": 0,
                "attempted": 0
              }
            },
            "Sig. str. %": 57.0,
            "Total str.": {
              "landed": 12,
              "attempted": 19
            },
            "Td": {
              "landed": 2,
              "attempted": 3
            },
            "Td %": 66.0,
            "Sub. att": 0,
            "Rev.": 0,
            "Ctrl": 156
          },
          "round2": {
            "KD": 0,
            "Sig. str.": {
              "landed": 2,
              "attempted": 6,
              "Head": {
                "landed": 1,
                "attempted": 5
              },
              "Body": {
                "landed": 0,
                "attempted": 0
              },
              "Leg": {
                "landed": 1,
                "attempted": 1
              },
              "Distance": {
                "landed": 2,
                "attempted": 6
              },
              "Clinch": {
                "landed": 0,
                "attempted": 0
              },
              "Ground": {
                "landed": 0,
                "attempted": 0
              }
            },
            "Sig. str. %": 33.0,
            "Total str.": {
              "landed": 2,
              "attempted": 6
            },
            "Td": {
              "landed": 1,
              "attempted": 1
            },
            "Td %": 100.0,
            "Sub. att": 1,
            "Rev.": 0,
            "Ctrl": 10
          }
        },
        "pre_comp": null
      }
    },
    {
      "fight_id": "98b7dd0ddc52cffb",
      "method": "Decision - Split",
      "round": "3",
      "time": "5:00",
      "time_format": "3 Rnd (5-5-5)",
      "referee": "Herb Dean",
      "details": [
        {
          "judge": "Ben Cartlidge",
          "score": "28 - 29."
        },
        {
          "judge": "Ron McCarthy",
          "score": "29 - 28."
        },
        {
          "judge": "Chris Flores",
          "score": "28 - 29."
        }
      ],
      "fighter1": {
        "id": "e4277e87a789d687",
        "name": "Dustin Jacoby",
        "nickname": "The Hanyak",
        "dob": "04/04/1988",
        "height": 75,
        "weight": 205,
        "reach": 76,
        "stance": "orthodox",
        "stats": {
          "SLpM": 5.33,
          "Str. Acc.:": 47.0,
          "SApM": 4.05,
          "TD. Avg.": 0.33,
          "TD. Acc.": 25.0,
          "TD, Def": 62.0,
          "Sub. Avg.": 0.0,
          "record": {
            "wins": 20,
            "losses": 9,
            "draws": 1
          }
        },
        "timestamp": "2025-02-10 14:30:45",
        "result": "L",
        "KD": 0,
        "Sig. str.": {
          "landed": 120,
          "attempted": 255,
          "Head": {
            "landed": 69,
            "attempted": 194
          },
          "Body": {
            "landed": 27,
            "attempted": 34
          },
          "Leg": {
            "landed": 24,
            "attempted": 27
          },
          "Distance": {
            "landed": 116,
            "attempted": 250
          },
          "Clinch": {
            "landed": 4,
            "attempted": 5
          },
          "Ground": {
            "landed": 0,
            "attempted": 0
          }
        },
        "Sig. str. %": 47.0,
        "Total str.": {
          "landed": 122,
          "attempted": 257
        },
        "Td": {
          "landed": 0,
          "attempted": 3
        },
        "Td %": 0.0,
        "Sub. att": "0",
        "Rev.": "0",
        "Ctrl": "0:05",
        "rounds": {
          "round1": {
            "KD": 0,
            "Sig. str.": {
              "landed": 34,
              "attempted": 66,
              "Head": {
                "landed": 12,
                "attempted": 38
              },
              "Body": {
                "landed": 12,
                "attempted": 16
              },
              "Leg": {
                "landed": 10,
                "attempted": 12
              },
              "Distance": {
                "landed": 34,
                "attempted": 66
              },
              "Clinch": {
                "landed": 0,
                "attempted": 0
              },
              "Ground": {
                "landed": 0,
                "attempted": 0
              }
            },
            "Sig. str. %": 51.0,
            "Total str.": {
              "landed": 35,
              "attempted": 67
            },
            "Td": {
              "landed": 0,
              "attempted": 1
            },
            "Td %": 0.0,
            "Sub. att": 0,
            "Rev.": 0,
            "Ctrl": 0
          },
          "round2": {
            "KD": 0,
            "Sig. str.": {
              "landed": 39,
              "attempted": 105,
              "Head": {
                "landed": 30,
                "attempted": 93
              },
              "Body": {
                "landed": 5,
                "attempted": 7
              },
              "Leg": {
                "landed": 4,
                "attempted": 5
              },
              "Distance": {
                "landed": 39,
                "attempted": 105
              },
              "Clinch": {
                "landed": 0,
                "attempted": 0
              },
              "Ground": {
                "landed": 0,
                "attempted": 0
              }
            },
            "Sig. str. %": 37.0,
            "Total str.": {
              "landed": 40,
              "attempted": 106
            },
            "Td": {
              "landed": 0,
              "attempted": 0
            },
            "Td %": 0,
            "Sub. att": 0,
            "Rev.": 0,
            "Ctrl": 5
          },
          "round3": {
            "KD": 0,
            "Sig. str.": {
              "landed": 47,
              "attempted": 84,
              "Head": {
                "landed": 27,
                "attempted": 63
              },
              "Body": {
                "landed": 10,
                "attempted": 11
              },
              "Leg": {
                "landed": 10,
                "attempted": 10
              },
              "Distance": {
                "landed": 43,
                "attempted": 79
              },
              "Clinch": {
                "landed": 4,
                "attempted": 5
              },
              "Ground": {
                "landed": 0,
                "attempted": 0
              }
            },
            "Sig. str. %": 55.0,
            "Total str.": {
              "landed": 47,
              "attempted": 84
            },
            "Td": {
              "landed": 0,
              "attempted": 2
            },
            "Td %": 0.0,
            "Sub. att": 0,
            "Rev.": 0,
            "Ctrl": 0
          }
        },
        "pre_comp": null
      },
      "fighter2": {
        "id": "749f572d1d3161fb",
        "name": "Khalil Rountree Jr.",
        "nickname": "",
        "dob": "26/02/1990",
        "height": 73,
        "weight": 205,
        "reach": 76,
        "stance": "southpaw",
        "stats": {
          "SLpM": 3.73,
          "Str. Acc.:": 38.0,
          "SApM": 4.51,
          "TD. Avg.": 0.0,
          "TD. Acc.": 0.0,
          "TD, Def": 58.0,
          "Sub. Avg.": 0.1,
          "record": {
            "wins": 14,
            "losses": 6,
            "draws": 0
          }
        },
        "timestamp": "2025-02-10 14:30:46",
        "result": "W",
        "KD": 0,
        "Sig. str.": {
          "landed": 85,
          "attempted": 237,
          "Head": {
            "landed": 49,
            "attempted": 193
          },
          "Body": {
            "landed": 18,
            "attempted": 23
          },
          "Leg": {
            "landed": 18,
            "attempted": 21
          },
          "Distance": {
            "landed": 80,
            "attempted": 231
          },
          "Clinch": {
            "landed": 5,
            "attempted": 6
          },
          "Ground": {
            "landed": 0,
            "attempted": 0
          }
        },
        "Sig. str. %": 35.0,
        "Total str.": {
          "landed": 88,
          "attempted": 241
        },
        "Td": {
          "landed": 0,
          "attempted": 0
        },
        "Td %": "---",
        "Sub. att": "0",
        "Rev.": "0",
        "Ctrl": "0:00",
        "rounds": {
          "round1": {
            "KD": 0,
            "Sig. str.": {
              "landed": 20,
              "attempted": 57,
              "Head": {
                "landed": 11,
                "attempted": 44
              },
              "Body": {
                "landed": 3,
                "attempted": 4
              },
              "Leg": {
                "landed": 6,
                "attempted": 9
              },
              "Distance": {
                "landed": 19,
                "attempted": 55
              },
              "Clinch": {
                "landed": 1,
                "attempted": 2
              },
              "Ground": {
                "landed": 0,
                "attempted": 0
              }
            },
            "Sig. str. %": 35.0,
            "Total str.": {
              "landed": 22,
              "attempted": 60
            },
            "Td": {
              "landed": 0,
              "attempted": 0
            },
            "Td %": 0,
            "Sub. att": 0,
            "Rev.": 0,
            "Ctrl": 0
          },
          "round2": {
            "KD": 0,
            "Sig. str.": {
              "landed": 35,
              "attempted": 88,
              "Head": {
                "landed": 20,
                "attempted": 72
              },
              "Body": {
                "landed": 7,
                "attempted": 8
              },
              "Leg": {
                "landed": 8,
                "attempted": 8
              },
              "Distance": {
                "landed": 35,
                "attempted": 88
              },
              "Clinch": {
                "landed": 0,
                "attempted": 0
              },
              "Ground": {
                "landed": 0,
                "attempted": 0
              }
            },
            "Sig. str. %": 39.0,
            "Total str.": {
              "landed": 36,
              "attempted": 89
            },
            "Td": {
              "landed": 0,
              "attempted": 0
            },
            "Td %": 0,
            "Sub. att": 0,
            "Rev.": 0,
            "Ctrl": 0
          },
          "round3": {
            "KD": 0,
            "Sig. str.": {
              "landed": 30,
              "attempted": 92,
              "Head": {
                "landed": 18,
                "attempted": 77
              },
              "Body": {
                "landed": 8,
                "attempted": 11
              },
              "Leg": {
                "landed": 4,
                "attempted": 4
              },
              "Distance": {
                "landed": 26,
                "attempted": 88
              },
              "Clinch": {
                "landed": 4,
                "attempted": 4
              },
              "Ground": {
                "landed": 0,
                "attempted": 0
              }
            },
            "Sig. str. %": 32.0,
            "Total str.": {
              "landed": 30,
              "attempted": 92
            },
            "Td": {
              "landed": 0,
              "attempted": 0
            },
            "Td %": 0,
            "Sub. att": 0,
            "Rev.": 0,
            "Ctrl": 0
          }
        },
        "pre_comp": null
      }
    },
    {
      "fight_id": "f32d918ee06cb83b",
      "method": "KO/TKO",
      "round": "1",
      "time": "4:09",
      "time_format": "3 Rnd (5-5-5)",
      "referee": "Dan Miragliotta",
      "details": [],
      "fighter1": {
        "id": "547afe1017e72dbe",
        "name": "Phil Hawes",
        "nickname": "No Hype",
        "dob": "08/01/1989",
        "height": 72,
        "weight": 185,
        "reach": 77,
        "stance": "orthodox",
        "stats": {
          "SLpM": 5.33,
          "Str. Acc.:": 59.0,
          "SApM": 3.72,
          "TD. Avg.": 2.11,
          "TD. Acc.": 34.0,
          "TD, Def": 90.0,
          "Sub. Avg.": 0.2,
          "record": {
            "wins": 12,
            "losses": 6,
            "draws": 0
          }
        },
        "timestamp": "2025-02-10 14:30:48",
        "result": "L",
        "KD": 0,
        "Sig. str.": {
          "landed": 11,
          "attempted": 26,
          "Head": {
            "landed": 5,
            "attempted": 15
          },
          "Body": {
            "landed": 5,
            "attempted": 9
          },
          "Leg": {
            "landed": 1,
            "attempted": 2
          },
          "Distance": {
            "landed": 11,
            "attempted": 26
          },
          "Clinch": {
            "landed": 0,
            "attempted": 0
          },
          "Ground": {
            "landed": 0,
            "attempted": 0
          }
        },
        "Sig. str. %": 42.0,
        "Total str.": {
          "landed": 15,
          "attempted": 31
        },
        "Td": {
          "landed": 1,
          "attempted": 1
        },
        "Td %": 100.0,
        "Sub. att": "0",
        "Rev.": "0",
        "Ctrl": "0:46",
        "rounds": {
          "round1": {
            "KD": 0,
            "Sig. str.": {
              "landed": 11,
              "attempted": 26,
              "Head": {
                "landed": 5,
                "attempted": 15
              },
              "Body": {
                "landed": 5,
                "attempted": 9
              },
              "Leg": {
                "landed": 1,
                "attempted": 2
              },
              "Distance": {
                "landed": 11,
                "attempted": 26
              },
              "Clinch": {
                "landed": 0,
                "attempted": 0
              },
              "Ground": {
                "landed": 0,
                "attempted": 0
              }
            },
            "Sig. str. %": 42.0,
            "Total str.": {
              "landed": 15,
              "attempted": 31
            },
            "Td": {
              "landed": 1,
              "attempted": 1
            },
            "Td %": 100.0,
            "Sub. att": 0,
            "Rev.": 0,
            "Ctrl": 46
          }
        },
        "pre_comp": null
      },
      "fighter2": {
        "id": "327d5f279895110d",
        "name": "Roman Dolidze",
        "nickname": "",
        "dob": "15/07/1988",
        "height": 74,
        "weight": 185,
        "reach": 76,
        "stance": "orthodox",
        "stats": {
          "SLpM": 3.16,
          "Str. Acc.:": 42.0,
          "SApM": 3.38,
          "TD. Avg.": 1.33,
          "TD. Acc.": 42.0,
          "TD, Def": 33.0,
          "Sub. Avg.": 1.1,
          "record": {
            "wins": 14,
            "losses": 3,
            "draws": 0
          }
        },
        "timestamp": "2025-02-10 14:30:49",
        "result": "W",
        "KD": 1,
        "Sig. str.": {
          "landed": 18,
          "attempted": 42,
          "Head": {
            "landed": 15,
            "attempted": 38
          },
          "Body": {
            "landed": 2,
            "attempted": 3
          },
          "Leg": {
            "landed": 1,
            "attempted": 1
          },
          "Distance": {
            "landed": 14,
            "attempted": 36
          },
          "Clinch": {
            "landed": 2,
            "attempted": 4
          },
          "Ground": {
            "landed": 2,
            "attempted": 2
          }
        },
        "Sig. str. %": 42.0,
        "Total str.": {
          "landed": 29,
          "attempted": 57
        },
        "Td": {
          "landed": 0,
          "attempted": 0
        },
        "Td %": "---",
        "Sub. att": "1",
        "Rev.": "0",
        "Ctrl": "0:02",
        "rounds": {
          "round1": {
            "KD": 1,
            "Sig. str.": {
              "landed": 18,
              "attempted": 42,
              "Head": {
                "landed": 15,
                "attempted": 38
              },
              "Body": {
                "landed": 2,
                "attempted": 3
              },
              "Leg": {
                "landed": 1,
                "attempted": 1
              },
              "Distance": {
                "landed": 14,
                "attempted": 36
              },
              "Clinch": {
                "landed": 2,
                "attempted": 4
              },
              "Ground": {
                "landed": 2,
                "attempted": 2
              }
            },
            "Sig. str. %": 42.0,
            "Total str.": {
              "landed": 29,
              "attempted": 57
            },
            "Td": {
              "landed": 0,
              "attempted": 0
            },
            "Td %": 0,
            "Sub. att": 1,
            "Rev.": 0,
            "Ctrl": 2
          }
        },
        "pre_comp": null
      }
    },
    {
      "fight_id": "5dcba156bd13e0c3",
      "method": "Submission",
      "round": "1",
      "time": "1:50",
      "time_format": "3 Rnd (5-5-5)",
      "referee": "Mark Smith",
      "details": [],
      "fighter1": {
        "id": "3738e68d2261e60f",
        "name": "Andrei Arlovski",
        "nickname": "The Pitbull",
        "dob": "04/02/1979",
        "height": 75,
        "weight": 240,
        "reach": 77,
        "stance": "orthodox",
        "stats": {
          "SLpM": 3.82,
          "Str. Acc.:": 45.0,
          "SApM": 3.22,
          "TD. Avg.": 0.37,
          "TD. Acc.": 35.0,
          "TD, Def": 76.0,
          "Sub. Avg.": 0.2,
          "record": {
            "wins": 34,
            "losses": 24,
            "draws": 0
          }
        },
        "timestamp": "2025-02-10 14:30:51",
        "result": "L",
        "KD": 0,
        "Sig. str.": {
          "landed": 2,
          "attempted": 5,
          "Head": {
            "landed": 1,
            "attempted": 3
          },
          "Body": {
            "landed": 0,
            "attempted": 1
          },
          "Leg": {
            "landed": 1,
            "attempted": 1
          },
          "Distance": {
            "landed": 2,
            "attempted": 5
          },
          "Clinch": {
            "landed": 0,
            "attempted": 0
          },
          "Ground": {
            "landed": 0,
            "attempted": 0
          }
        },
        "Sig. str. %": 40.0,
        "Total str.": {
          "landed": 3,
          "attempted": 6
        },
        "Td": {
          "landed": 0,
          "attempted": 0
        },
        "Td %": "---",
        "Sub. att": "0",
        "Rev.": "0",
        "Ctrl": "0:00",
        "rounds": {
          "round1": {
            "KD": 0,
            "Sig. str.": {
              "landed": 2,
              "attempted": 5,
              "Head": {
                "landed": 1,
                "attempted": 3
              },
              "Body": {
                "landed": 0,
                "attempted": 1
              },
              "Leg": {
                "landed": 1,
                "attempted": 1
              },
              "Distance": {
                "landed": 2,
                "attempted": 5
              },
              "Clinch": {
                "landed": 0,
                "attempted": 0
              },
              "Ground": {
                "landed": 0,
                "attempted": 0
              }
            },
            "Sig. str. %": 40.0,
            "Total str.": {
              "landed": 3,
              "attempted": 6
            },
            "Td": {
              "landed": 0,
              "attempted": 0
            },
            "Td %": 0,
            "Sub. att": 0,
            "Rev.": 0,
            "Ctrl": 0
          }
        },
        "pre_comp": null
      },
      "fighter2": {
        "id": "ab943cd2c3c17825",
        "name": "Marcos Rogerio de Lima",
        "nickname": "Pezao",
        "dob": "25/06/1985",
        "height": 73,
        "weight": 253,
        "reach": 75,
        "stance": "orthodox",
        "stats": {
          "SLpM": 3.7,
          "Str. Acc.:": 57.0,
          "SApM": 2.9,
          "TD. Avg.": 1.4,
          "TD. Acc.": 45.0,
          "TD, Def": 59.0,
          "Sub. Avg.": 0.5,
          "record": {
            "wins": 22,
            "losses": 10,
            "draws": 1
          }
        },
        "timestamp": "2025-02-10 14:30:52",
        "result": "W",
        "KD": 1,
        "Sig. str.": {
          "landed": 6,
          "attempted": 11,
          "Head": {
            "landed": 3,
            "attempted": 8
          },
          "Body": {
            "landed": 1,
            "attempted": 1
          },
          "Leg": {
            "landed": 2,
            "attempted": 2
          },
          "Distance": {
            "landed": 5,
            "attempted": 9
          },
          "Clinch": {
            "landed": 0,
            "attempted": 0
          },
          "Ground": {
            "landed": 1,
            "attempted": 2
          }
        },
        "Sig. str. %": 54.0,
        "Total str.": {
          "landed": 25,
          "attempted": 33
        },
        "Td": {
          "landed": 0,
          "attempted": 0
        },
        "Td %": "---",
        "Sub. att": "1",
        "Rev.": "0",
        "Ctrl": "1:30",
        "rounds": {
          "round1": {
            "KD": 1,
            "Sig. str.": {
              "landed": 6,
              "attempted": 11,
              "Head": {
                "landed": 3,
                "attempted": 8
              },
              "Body": {
                "landed": 1,
                "attempted": 1
              },
              "Leg": {
                "landed": 2,
                "attempted": 2
              },
              "Distance": {
                "landed": 5,
                "attempted": 9
              },
              "Clinch": {
                "landed": 0,
                "attempted": 0
              },
              "Ground": {
                "landed": 1,
                "attempted": 2
              }
            },
            "Sig. str. %": 54.0,
            "Total str.": {
              "landed": 25,
              "attempted": 33
            },
            "Td": {
              "landed": 0,
              "attempted": 0
            },
            "Td %": 0,
            "Sub. att": 1,
            "Rev.": 0,
            "Ctrl": 90
          }
        },
        "pre_comp": null
      }
    },
    {
      "fight_id": "d6d141afdd31c3f1",
      "method": "Submission",
      "round": "2",
      "time": "3:04",
      "time_format": "3 Rnd (5-5-5)",
      "referee": "Chris Tognoni",
      "details": [],
      "fighter1": {
        "id": "8d20d76af3f213ce",
        "name": "Joseph Holmes",
        "nickname": "Uglyman Joe",
        "dob": "04/07/1995",
        "height": 76,
        "weight": 185,
        "reach": 80,
        "stance": "orthodox",
        "stats": {
          "SLpM": 2.88,
          "Str. Acc.:": 53.0,
          "SApM": 3.08,
          "TD. Avg.": 1.49,
          "TD. Acc.": 40.0,
          "TD, Def": 50.0,
          "Sub. Avg.": 0.8,
          "record": {
            "wins": 8,
            "losses": 4,
            "draws": 0
          }
        },
        "timestamp": "2025-02-10 14:30:54",
        "result": "L",
        "KD": 0,
        "Sig. str.": {
          "landed": 20,
          "attempted": 40,
          "Head": {
            "landed": 8,
            "attempted": 24
          },
          "Body": {
            "landed": 5,
            "attempted": 7
          },
          "Leg": {
            "landed": 7,
            "attempted": 9
          },
          "Distance": {
            "landed": 19,
            "attempted": 37
          },
          "Clinch": {
            "landed": 0,
            "attempted": 1
          },
          "Ground": {
            "landed": 1,
            "attempted": 2
          }
        },
        "Sig. str. %": 50.0,
        "Total str.": {
          "landed": 21,
          "attempted": 42
        },
        "Td": {
          "landed": 0,
          "attempted": 0
        },
        "Td %": "---",
        "Sub. att": "0",
        "Rev.": "1",
        "Ctrl": "0:39",
        "rounds": {
          "round1": {
            "KD": 0,
            "Sig. str.": {
              "landed": 18,
              "attempted": 36,
              "Head": {
                "landed": 7,
                "attempted": 21
              },
              "Body": {
                "landed": 5,
                "attempted": 7
              },
              "Leg": {
                "landed": 6,
                "attempted": 8
              },
              "Distance": {
                "landed": 17,
                "attempted": 33
              },
              "Clinch": {
                "landed": 0,
                "attempted": 1
              },
              "Ground": {
                "landed": 1,
                "attempted": 2
              }
            },
            "Sig. str. %": 50.0,
            "Total str.": {
              "landed": 19,
              "attempted": 38
            },
            "Td": {
              "landed": 0,
              "attempted": 0
            },
            "Td %": 0,
            "Sub. att": 0,
            "Rev.": 1,
            "Ctrl": 39
          },
          "round2": {
            "KD": 0,
            "Sig. str.": {
              "landed": 2,
              "attempted": 4,
              "Head": {
                "landed": 1,
                "attempted": 3
              },
              "Body": {
                "landed": 0,
                "attempted": 0
              },
              "Leg": {
                "landed": 1,
                "attempted": 1
              },
              "Distance": {
                "landed": 2,
                "attempted": 4
              },
              "Clinch": {
                "landed": 0,
                "attempted": 0
              },
              "Ground": {
                "landed": 0,
                "attempted": 0
              }
            },
            "Sig. str. %": 50.0,
            "Total str.": {
              "landed": 2,
              "attempted": 4
            },
            "Td": {
              "landed": 0,
              "attempted": 0
            },
            "Td %": 0,
            "Sub. att": 0,
            "Rev.": 0,
            "Ctrl": 0
          }
        },
        "pre_comp": null
      },
      "fighter2": {
        "id": "285ae0b4a68221f4",
        "name": "JunYong Park",
        "nickname": "The Iron Turtle",
        "dob": "27/02/1991",
        "height": 70,
        "weight": 185,
        "reach": 73,
        "stance": "orthodox",
        "stats": {
          "SLpM": 4.77,
          "Str. Acc.:": 51.0,
          "SApM": 3.42,
          "TD. Avg.": 1.85,
          "TD. Acc.": 47.0,
          "TD, Def": 57.0,
          "Sub. Avg.": 0.9,
          "record": {
            "wins": 18,
            "losses": 6,
            "draws": 0
          }
        },
        "timestamp": "2025-02-10 14:30:55",
        "result": "W",
        "KD": 0,
        "Sig. str.": {
          "landed": 18,
          "attempted": 33,
          "Head": {
            "landed": 13,
            "attempted": 26
          },
          "Body": {
            "landed": 0,
            "attempted": 0
          },
          "Leg": {
            "landed": 5,
            "attempted": 7
          },
          "Distance": {
            "landed": 14,
            "attempted": 28
          },
          "Clinch": {
            "landed": 0,
            "attempted": 0
          },
          "Ground": {
            "landed": 4,
            "attempted": 5
          }
        },
        "Sig. str. %": 54.0,
        "Total str.": {
          "landed": 48,
          "attempted": 76
        },
        "Td": {
          "landed": 2,
          "attempted": 4
        },
        "Td %": 50.0,
        "Sub. att": "2",
        "Rev.": "0",
        "Ctrl": "4:37",
        "rounds": {
          "round1": {
            "KD": 0,
            "Sig. str.": {
              "landed": 12,
              "attempted": 24,
              "Head": {
                "landed": 8,
                "attempted": 19
              },
              "Body": {
                "landed": 0,
                "attempted": 0
              },
              "Leg": {
                "landed": 4,
                "attempted": 5
              },
              "Distance": {
                "landed": 12,
                "attempted": 24
              },
              "Clinch": {
                "landed": 0,
                "attempted": 0
              },
              "Ground": {
                "landed": 0,
                "attempted": 0
              }
            },
            "Sig. str. %": 50.0,
            "Total str.": {
              "landed": 22,
              "attempted": 36
            },
            "Td": {
              "landed": 1,
              "attempted": 2
            },
            "Td %": 50.0,
            "Sub. att": 0,
            "Rev.": 0,
            "Ctrl": 115
          },
          "round2": {
            "KD": 0,
            "Sig. str.": {
              "landed": 6,
              "attempted": 9,
              "Head": {
                "landed": 5,
                "attempted": 7
              },
              "Body": {
                "landed": 0,
                "attempted": 0
              },
              "Leg": {
                "landed": 1,
                "attempted": 2
              },
              "Distance": {
                "landed": 2,
                "attempted": 4
              },
              "Clinch": {
                "landed": 0,
                "attempted": 0
              },
              "Ground": {
                "landed": 4,
                "attempted": 5
              }
            },
            "Sig. str. %": 66.0,
            "Total str.": {
              "landed": 26,
              "attempted": 40
            },
            "Td": {
              "landed": 1,
              "attempted": 2
            },
            "Td %": 50.0,
            "Sub. att": 2,
            "Rev.": 0,
            "Ctrl": 162
          }
        },
        "pre_comp": null
      }
    },
    {
      "fight_id": "86dff1593d8b9a1f",
      "method": "KO/TKO",
      "round": "1",
      "time": "1:32",
      "time_format": "3 Rnd (5-5-5)",
      "referee": "Herb Dean",
      "details": [],
      "fighter1": {
        "id": "971246648e162f0d",
        "name": "Chase Hooper",
        "nickname": "The Dream",
        "dob": "13/09/1999",
        "height": 73,
        "weight": 155,
        "reach": 74,
        "stance": "southpaw",
        "stats": {
          "SLpM": 4.97,
          "Str. Acc.:": 52.0,
          "SApM": 3.26,
          "TD. Avg.": 1.83,
          "TD. Acc.": 27.0,
          "TD, Def": 57.0,
          "Sub. Avg.": 2.4,
          "record": {
            "wins": 15,
            "losses": 3,
            "draws": 1
          }
        },
        "timestamp": "2025-02-10 14:30:57",
        "result": "L",
        "KD": 0,
        "Sig. str.": {
          "landed": 10,
          "attempted": 30,
          "Head": {
            "landed": 7,
            "attempted": 25
          },
          "Body": {
            "landed": 2,
            "attempted": 4
          },
          "Leg": {
            "landed": 1,
            "attempted": 1
          },
          "Distance": {
            "landed": 10,
            "attempted": 30
          },
          "Clinch": {
            "landed": 0,
            "attempted": 0
          },
          "Ground": {
            "landed": 0,
            "attempted": 0
          }
        },
        "Sig. str. %": 33.0,
        "Total str.": {
          "landed": 10,
          "attempted": 32
        },
        "Td": {
          "landed": 0,
          "attempted": 1
        },
        "Td %": 0.0,
        "Sub. att": "0",
        "Rev.": "0",
        "Ctrl": "0:00",
        "rounds": {
          "round1": {
            "KD": 0,
            "Sig. str.": {
              "landed": 10,
              "attempted": 30,
              "Head": {
                "landed": 7,
                "attempted": 25
              },
              "Body": {
                "landed": 2,
                "attempted": 4
              },
              "Leg": {
                "landed": 1,
                "attempted": 1
              },
              "Distance": {
                "landed": 10,
                "attempted": 30
              },
              "Clinch": {
                "landed": 0,
                "attempted": 0
              },
              "Ground": {
                "landed": 0,
                "attempted": 0
              }
            },
            "Sig. str. %": 33.0,
            "Total str.": {
              "landed": 10,
              "attempted": 32
            },
            "Td": {
              "landed": 0,
              "attempted": 1
            },
            "Td %": 0.0,
            "Sub. att": 0,
            "Rev.": 0,
            "Ctrl": 0
          }
        },
        "pre_comp": null
      },
      "fighter2": {
        "id": "97cf1a2c7c5e7889",
        "name": "Steve Garcia",
        "nickname": "Mean Machine",
        "dob": "22/05/1992",
        "height": 72,
        "weight": 145,
        "reach": 75,
        "stance": "southpaw",
        "stats": {
          "SLpM": 5.04,
          "Str. Acc.:": 56.0,
          "SApM": 2.34,
          "TD. Avg.": 1.17,
          "TD. Acc.": 40.0,
          "TD, Def": 88.0,
          "Sub. Avg.": 0.6,
          "record": {
            "wins": 17,
            "losses": 5,
            "draws": 0
          }
        },
        "timestamp": "2025-02-10 14:30:58",
        "result": "W",
        "KD": 3,
        "Sig. str.": {
          "landed": 29,
          "attempted": 44,
          "Head": {
            "landed": 19,
            "attempted": 33
          },
          "Body": {
            "landed": 7,
            "attempted": 8
          },
          "Leg": {
            "landed": 3,
            "attempted": 3
          },
          "Distance": {
            "landed": 26,
            "attempted": 40
          },
          "Clinch": {
            "landed": 0,
            "attempted": 0
          },
          "Ground": {
            "landed": 3,
            "attempted": 4
          }
        },
        "Sig. str. %": 65.0,
        "Total str.": {
          "landed": 31,
          "attempted": 46
        },
        "Td": {
          "landed": 0,
          "attempted": 0
        },
        "Td %": "---",
        "Sub. att": "0",
        "Rev.": "0",
        "Ctrl": "0:17",
        "rounds": {
          "round1": {
            "KD": 3,
            "Sig. str.": {
              "landed": 29,
              "attempted": 44,
              "Head": {
                "landed": 19,
                "attempted": 33
              },
              "Body": {
                "landed": 7,
                "attempted": 8
              },
              "Leg": {
                "landed": 3,
                "attempted": 3
              },
              "Distance": {
                "landed": 26,
                "attempted": 40
              },
              "Clinch": {
                "landed": 0,
                "attempted": 0
              },
              "Ground": {
                "landed": 3,
                "attempted": 4
              }
            },
            "Sig. str. %": 65.0,
            "Total str.": {
              "landed": 31,
              "attempted": 46
            },
            "Td": {
              "landed": 0,
              "attempted": 0
            },
            "Td %": 0,
            "Sub. att": 0,
            "Rev.": 0,
            "Ctrl": 17
          }
        },
        "pre_comp": null
      }
    },
    {
      "fight_id": "44abbf6b947be6de",
      "method": "Decision - Unanimous",
      "round": "3",
      "time": "5:00",
      "time_format": "3 Rnd (5-5-5)",
      "referee": "Mark Smith",
      "details": [
        {
          "judge": "Adalaide Byrd",
          "score": "27 - 30."
        },
        {
          "judge": "Tony Weeks",
          "score": "28 - 29."
        },
        {
          "judge": "Ben Cartlidge",
          "score": "28 - 29."
        }
      ],
      "fighter1": {
        "id": "7f6ed67d3ed3c036",
        "name": "Cody Durden",
        "nickname": "Custom Made",
        "dob": "29/03/1991",
        "height": 67,
        "weight": 125,
        "reach": 67,
        "stance": "southpaw",
        "stats": {
          "SLpM": 3.52,
          "Str. Acc.:": 45.0,
          "SApM": 4.29,
          "TD. Avg.": 4.06,
          "TD. Acc.": 47.0,
          "TD, Def": 73.0,
          "Sub. Avg.": 0.8,
          "record": {
            "wins": 17,
            "losses": 7,
            "draws": 1
          }
        },
        "timestamp": "2025-02-10 14:31:00",
        "result": "W",
        "KD": 0,
        "Sig. str.": {
          "landed": 17,
          "attempted": 37,
          "Head": {
            "landed": 13,
            "attempted": 33
          },
          "Body": {
            "landed": 3,
            "attempted": 3
          },
          "Leg": {
            "landed": 1,
            "attempted": 1
          },
          "Distance": {
            "landed": 7,
            "attempted": 20
          },
          "Clinch": {
            "landed": 0,
            "attempted": 0
          },
          "Ground": {
            "landed": 10,
            "attempted": 17
          }
        },
        "Sig. str. %": 45.0,
        "Total str.": {
          "landed": 51,
          "attempted": 95
        },
        "Td": {
          "landed": 4,
          "attempted": 8
        },
        "Td %": 50.0,
        "Sub. att": "0",
        "Rev.": "0",
        "Ctrl": "12:32",
        "rounds": {
          "round1": {
            "KD": 0,
            "Sig. str.": {
              "landed": 9,
              "attempted": 16,
              "Head": {
                "landed": 8,
                "attempted": 15
              },
              "Body": {
                "landed": 1,
                "attempted": 1
              },
              "Leg": {
                "landed": 0,
                "attempted": 0
              },
              "Distance": {
                "landed": 2,
                "attempted": 6
              },
              "Clinch": {
                "landed": 0,
                "attempted": 0
              },
              "Ground": {
                "landed": 7,
                "attempted": 10
              }
            },
            "Sig. str. %": 56.0,
            "Total str.": {
              "landed": 13,
              "attempted": 29
            },
            "Td": {
              "landed": 1,
              "attempted": 1
            },
            "Td %": 100.0,
            "Sub. att": 0,
            "Rev.": 0,
            "Ctrl": 267
          },
          "round2": {
            "KD": 0,
            "Sig. str.": {
              "landed": 3,
              "attempted": 11,
              "Head": {
                "landed": 2,
                "attempted": 10
              },
              "Body": {
                "landed": 1,
                "attempted": 1
              },
              "Leg": {
                "landed": 0,
                "attempted": 0
              },
              "Distance": {
                "landed": 0,
                "attempted": 4
              },
              "Clinch": {
                "landed": 0,
                "attempted": 0
              },
              "Ground": {
                "landed": 3,
                "attempted": 7
              }
            },
            "Sig. str. %": 27.0,
            "Total str.": {
              "landed": 23,
              "attempted": 39
            },
            "Td": {
              "landed": 1,
              "attempted": 4
            },
            "Td %": 25.0,
            "Sub. att": 0,
            "Rev.": 0,
            "Ctrl": 265
          },
          "round3": {
            "KD": 0,
            "Sig. str.": {
              "landed": 5,
              "attempted": 10,
              "Head": {
                "landed": 3,
                "attempted": 8
              },
              "Body": {
                "landed": 1,
                "attempted": 1
              },
              "Leg": {
                "landed": 1,
                "attempted": 1
              },
              "Distance": {
                "landed": 5,
                "attempted": 10
              },
              "Clinch": {
                "landed": 0,
                "attempted": 0
              },
              "Ground": {
                "landed": 0,
                "attempted": 0
              }
            },
            "Sig. str. %": 50.0,
            "Total str.": {
              "landed": 15,
              "attempted": 27
            },
            "Td": {
              "landed": 2,
              "attempted": 3
            },
            "Td %": 66.0,
            "Sub. att": 0,
            "Rev.": 0,
            "Ctrl": 220
          }
        },
        "pre_comp": null
      },
      "fighter2": {
        "id": "b15862fcd6ded451",
        "name": "Carlos Mota",
        "nickname": "Tizil",
        "dob": "15/04/1995",
        "height": 64,
        "weight": 125,
        "reach": 69,
        "stance": "orthodox",
        "stats": {
          "SLpM": 0.8,
          "Str. Acc.:": 41.0,
          "SApM": 1.13,
          "TD. Avg.": 0.0,
          "TD. Acc.": 0.0,
          "TD, Def": 50.0,
          "Sub. Avg.": 1.0,
          "record": {
            "wins": 8,
            "losses": 2,
            "draws": 0
          }
        },
        "timestamp": "2025-02-10 14:31:01",
        "result": "L",
        "KD": 0,
        "Sig. str.": {
          "landed": 12,
          "attempted": 29,
          "Head": {
            "landed": 6,
            "attempted": 19
          },
          "Body": {
            "landed": 5,
            "attempted": 9
          },
          "Leg": {
            "landed": 1,
            "attempted": 1
          },
          "Distance": {
            "landed": 7,
            "attempted": 22
          },
          "Clinch": {
            "landed": 0,
            "attempted": 0
          },
          "Ground": {
            "landed": 5,
            "attempted": 7
          }
        },
        "Sig. str. %": 41.0,
        "Total str.": {
          "landed": 36,
          "attempted": 62
        },
        "Td": {
          "landed": 0,
          "attempted": 0
        },
        "Td %": "---",
        "Sub. att": "1",
        "Rev.": "1",
        "Ctrl": "0:11",
        "rounds": {
          "round1": {
            "KD": 0,
            "Sig. str.": {
              "landed": 2,
              "attempted": 4,
              "Head": {
                "landed": 1,
                "attempted": 3
              },
              "Body": {
                "landed": 0,
                "attempted": 0
              },
              "Leg": {
                "landed": 1,
                "attempted": 1
              },
              "Distance": {
                "landed": 1,
                "attempted": 3
              },
              "Clinch": {
                "landed": 0,
                "attempted": 0
              },
              "Ground": {
                "landed": 1,
                "attempted": 1
              }
            },
            "Sig. str. %": 50.0,
            "Total str.": {
              "landed": 6,
              "attempted": 12
            },
            "Td": {
              "landed": 0,
              "attempted": 0
            },
            "Td %": 0,
            "Sub. att": 0,
            "Rev.": 0,
            "Ctrl": 0
          },
          "round2": {
            "KD": 0,
            "Sig. str.": {
              "landed": 3,
              "attempted": 6,
              "Head": {
                "landed": 2,
                "attempted": 5
              },
              "Body": {
                "landed": 1,
                "attempted": 1
              },
              "Leg": {
                "landed": 0,
                "attempted": 0
              },
              "Distance": {
                "landed": 2,
                "attempted": 4
              },
              "Clinch": {
                "landed": 0,
                "attempted": 0
              },
              "Ground": {
                "landed": 1,
                "attempted": 2
              }
            },
            "Sig. str. %": 50.0,
            "Total str.": {
              "landed": 18,
              "attempted": 25
            },
            "Td": {
              "landed": 0,
              "attempted": 0
            },
            "Td %": 0,
            "Sub. att": 1,
            "Rev.": 0,
            "Ctrl": 0
          },
          "round3": {
            "KD": 0,
            "Sig. str.": {
              "landed": 7,
              "attempted": 19,
              "Head": {
                "landed": 3,
                "attempted": 11
              },
              "Body": {
                "landed": 4,
                "attempted": 8
              },
              "Leg": {
                "landed": 0,
                "attempted": 0
              },
              "Distance": {
                "landed": 4,
                "attempted": 15
              },
              "Clinch": {
                "landed": 0,
                "attempted": 0
              },
              "Ground": {
                "landed": 3,
                "attempted": 4
              }
            },
            "Sig. str. %": 36.0,
            "Total str.": {
              "landed": 12,
              "attempted": 25
            },
            "Td": {
              "landed": 0,
              "attempted": 0
            },
            "Td %": 0,
            "Sub. att": 0,
            "Rev.": 1,
            "Ctrl": 11
          }
        },
        "pre_comp": null
      }
    },
    {
      "fight_id": "fdb9d29cf0edc16a",
      "method": "Submission",
      "round": "1",
      "time": "4:07",
      "time_format": "3 Rnd (5-5-5)",
      "referee": "Chris Tognoni",
      "details": [],
      "fighter1": {
        "id": "5ec591b78349ba7e",
        "name": "Christian Rodriguez",
        "nickname": "",
        "dob": "17/12/1997",
        "height": 67,
        "weight": 145,
        "reach": 71,
        "stance": "orthodox",
        "stats": {
          "SLpM": 3.54,
          "Str. Acc.:": 48.0,
          "SApM": 2.41,
          "TD. Avg.": 1.21,
          "TD. Acc.": 53.0,
          "TD, Def": 69.0,
          "Sub. Avg.": 1.2,
          "record": {
            "wins": 12,
            "losses": 2,
            "draws": 0
          }
        },
        "timestamp": "2025-02-10 14:31:03",
        "result": "W",
        "KD": 0,
        "Sig. str.": {
          "landed": 9,
          "attempted": 23,
          "Head": {
            "landed": 8,
            "attempted": 21
          },
          "Body": {
            "landed": 0,
            "attempted": 0
          },
          "Leg": {
            "landed": 1,
            "attempted": 2
          },
          "Distance": {
            "landed": 8,
            "attempted": 21
          },
          "Clinch": {
            "landed": 0,
            "attempted": 1
          },
          "Ground": {
            "landed": 1,
            "attempted": 1
          }
        },
        "Sig. str. %": 39.0,
        "Total str.": {
          "landed": 15,
          "attempted": 30
        },
        "Td": {
          "landed": 0,
          "attempted": 2
        },
        "Td %": 0.0,
        "Sub. att": "1",
        "Rev.": "0",
        "Ctrl": "0:56",
        "rounds": {
          "round1": {
            "KD": 0,
            "Sig. str.": {
              "landed": 9,
              "attempted": 23,
              "Head": {
                "landed": 8,
                "attempted": 21
              },
              "Body": {
                "landed": 0,
                "attempted": 0
              },
              "Leg": {
                "landed": 1,
                "attempted": 2
              },
              "Distance": {
                "landed": 8,
                "attempted": 21
              },
              "Clinch": {
                "landed": 0,
                "attempted": 1
              },
              "Ground": {
                "landed": 1,
                "attempted": 1
              }
            },
            "Sig. str. %": 39.0,
            "Total str.": {
              "landed": 15,
              "attempted": 30
            },
            "Td": {
              "landed": 0,
              "attempted": 2
            },
            "Td %": 0.0,
            "Sub. att": 1,
            "Rev.": 0,
            "Ctrl": 56
          }
        },
        "pre_comp": null
      },
      "fighter2": {
        "id": "69888118d968ba52",
        "name": "Joshua Weems",
        "nickname": "Wide Open",
        "dob": "05/05/1994",
        "height": 68,
        "weight": 135,
        "reach": 69,
        "stance": "orthodox",
        "stats": {
          "SLpM": 5.25,
          "Str. Acc.:": 64.0,
          "SApM": 3.34,
          "TD. Avg.": 4.77,
          "TD. Acc.": 40.0,
          "TD, Def": 100.0,
          "Sub. Avg.": 0.0,
          "record": {
            "wins": 11,
            "losses": 3,
            "draws": 0
          }
        },
        "timestamp": "2025-02-10 14:31:04",
        "result": "L",
        "KD": 0,
        "Sig. str.": {
          "landed": 18,
          "attempted": 26,
          "Head": {
            "landed": 9,
            "attempted": 15
          },
          "Body": {
            "landed": 6,
            "attempted": 7
          },
          "Leg": {
            "landed": 3,
            "attempted": 4
          },
          "Distance": {
            "landed": 12,
            "attempted": 19
          },
          "Clinch": {
            "landed": 6,
            "attempted": 7
          },
          "Ground": {
            "landed": 0,
            "attempted": 0
          }
        },
        "Sig. str. %": 69.0,
        "Total str.": {
          "landed": 22,
          "attempted": 32
        },
        "Td": {
          "landed": 2,
          "attempted": 3
        },
        "Td %": 66.0,
        "Sub. att": "0",
        "Rev.": "0",
        "Ctrl": "1:03",
        "rounds": {
          "round1": {
            "KD": 0,
            "Sig. str.": {
              "landed": 18,
              "attempted": 26,
              "Head": {
                "landed": 9,
                "attempted": 15
              },
              "Body": {
                "landed": 6,
                "attempted": 7
              },
              "Leg": {
                "landed": 3,
                "attempted": 4
              },
              "Distance": {
                "landed": 12,
                "attempted": 19
              },
              "Clinch": {
                "landed": 6,
                "attempted": 7
              },
              "Ground": {
                "landed": 0,
                "attempted": 0
              }
            },
            "Sig. str. %": 69.0,
            "Total str.": {
              "landed": 22,
              "attempted": 32
            },
            "Td": {
              "landed": 2,
              "attempted": 3
            },
            "Td %": 66.0,
            "Sub. att": 0,
            "Rev.": 0,
            "Ctrl": 63
          }
        },
        "pre_comp": null
      }
    }
  ]
}