{
  "fight_id": "bc6d70ab959dce70",
  "method": "",
  "round": "",
  "time": "",
  "time_format": "",
  "referee": "",
  "details": [],
  "fighter1": {
    "id": "5987b2458f4b5290",
    "name": "Ricky Simon",
    "nickname": "",
    "dob": "31/08/1992",
    "height": 66,
    "weight": 135,
    "reach": 69,
    "stance": "orthodox",
    "stats": {
      "SLpM": 2.99,
      "Str. Acc.:": 43.0,
      "SApM": 3.84,
      "TD. Avg.": 5.2,
      "TD. Acc.": 44.0,
      "TD, Def": 75.0,
      "Sub. Avg.": 0.3,
      "record": {
        "wins": 20,
        "losses": 6,
        "draws": 0
      }
    },
    "timestamp": "2025-02-13 16:40:22",
    "result": "",
    "KD": 0,
    "Sig. str.": {
      "landed": 0,
      "attempted": 0,
      "Head": {
        "landed": 0,
        "attempted": 0
      },
      "Body": {
        "landed": 0,
        "attempted": 0
      },
      "Leg": {
        "landed": 0,
        "attempted": 0
      },
      "Distance": {
        "landed": 0,
        "attempted": 0
      },
      "Clinch": {
        "landed": 0,
        "attempted": 0
      },
      "Ground": {
        "landed": 0,
        "attempted": 0
      }
    },
    "Sig. str. %": 0.0,
    "Total str.": {
      "landed": 0,
      "attempted": 0
    },
    "Td": {
      "landed": 0,
      "attempted": 0
    },
    "Td %": 0.0,
    "Sub. att": 0,
    "Rev.": 0,
    "Ctrl": "",
    "rounds": {},
    "pre_comp": null
  },
  "fighter2": {
    "id": "bbab3baf66128ae2",
    "name": "Javid Basharat",
    "nickname": "The Snow Leopard",
    "dob": "07/09/1995",
    "height": 69,
    "weight": 135,
    "reach": 69,
    "stance": "orthodox",
    "stats": {
      "SLpM": 5.42,
      "Str. Acc.:": 53.0,
      "SApM": 2.97,
      "TD. Avg.": 1.7,
      "TD. Acc.": 40.0,
      "TD, Def": 85.0,
      "Sub. Avg.": 0.2,
      "record": {
        "wins": 14,
        "losses": 1,
        "draws": 0
      }
    },
    "timestamp": "2025-02-13 16:40:24",
    "result": "",
    "KD": 0,
    "Sig. str.": {
      "landed": 0,
      "attempted": 0,
      "Head": {
        "landed": 0,
        "attempted": 0
      },
      "Body": {
        "landed": 0,
        "attempted": 0
      },
      "Leg": {
        "landed": 0,
        "attempted": 0
      },
      "Distance": {
        "landed": 0,
        "attempted": 0
      },
      "Clinch": {
        "landed": 0,
        "attempted": 0
      },
      "Ground": {
        "landed": 0,
        "attempted": 0
      }
    },
    "Sig. str. %": 0.0,
    "Total str.": {
      "landed": 0,
      "attempted": 0
    },
    "Td": {
      "landed": 0,
      "attempted": 0
    },
    "Td %": 0.0,
    "Sub. att": 0,
    "Rev.": 0,
    "Ctrl": "",
    "rounds": {},
    "pre_comp": null
  }
}